wagtailcharts/__init__.py
wagtailcharts/apps.py
wagtailcharts/blocks.py
wagtailcharts/tests.py
wagtailcharts/static/wagtailcharts/css/jspreadsheet.css
wagtailcharts/static/wagtailcharts/css/jspreadsheet.theme.css
wagtailcharts/static/wagtailcharts/css/jsuites.css
wagtailcharts/static/wagtailcharts/css/wagtailcharts.css
wagtailcharts/static/wagtailcharts/js/chart-dataset.js
wagtailcharts/static/wagtailcharts/js/chart-types.js
wagtailcharts/static/wagtailcharts/js/chart.js
wagtailcharts/static/wagtailcharts/js/chartjs-plugin-datalabels.min.js
wagtailcharts/static/wagtailcharts/js/jspreadsheet.js
wagtailcharts/static/wagtailcharts/js/jsuites.js
wagtailcharts/static/wagtailcharts/js/stacked-100.js
wagtailcharts/static/wagtailcharts/js/wagtailcharts.js
wagtailcharts/templates/wagtailcharts/blocks/chart_block.html
wagtailcharts/templates/wagtailcharts/blocks/settings.html
wagtailcharts/templates/wagtailcharts/tags/render_charts.html
wagtailcharts/templatetags/__init__.py
wagtailcharts/templatetags/wagtailcharts_tags.py
wagtailcharts-0.6.3.dist-info/LICENSE.txt
wagtailcharts-0.6.3.dist-info/METADATA
wagtailcharts-0.6.3.dist-info/WHEEL
wagtailcharts-0.6.3.dist-info/top_level.txt
wagtailcharts-0.6.3.dist-info/RECORD
